{
  "timeframe" : {
    "type" : "OFFSET",
    "offsetDurationValue" : 72,
    "offsetDurationUnit" : "HOURS",
    "offsetShiftValue" : null,
    "offsetShiftUnit" : null,
    "customRangeStart" : null,
    "customRangeEnd" : null
  },
  "session" : {
    "name" : "y_Production",
    "id" : "y_Production",
    "sessionType" : "live",
    "timeFrameStart" : -1,
    "timeFrameEnd" : -1
  },
  "application" : "B2C",
  "locked" : false,
  "tiles" : [ {
    "id" : "7a52d51b-1458-4ff3-bf13-2e1395bb532c",
    "name" : "",
    "tileType" : "CHART_TILE_METER",
    "overrideSession" : false,
    "session" : null,
    "overrideApplication" : false,
    "application" : null,
    "comparisonTimeframe" : false,
    "timeframe" : null,
    "description" : "Page Class Average Response Time",
    "sizeX" : 1,
    "sizeY" : 1,
    "row" : 1,
    "column" : 1,
    "bounds" : "80,0,1920,320",
    "fixed" : false,
    "chartTile" : {
      "leftMeasures" : [ {
        "id" : "fafab66e-90cb-4948-a78c-2ede002bdcb1",
        "measureIdentifier" : {
          "keyId" : "Page Types",
          "metricGroupKeyId" : "Business Transaction Results",
          "metricKeyId" : "Value",
          "parentKeyId" : "Page Types",
          "agentName" : "",
          "agentHost" : "",
          "collectorId" : "",
          "application" : ""
        },
        "name" : "Value",
        "measureType" : "TransactionMeasure",
        "unitId" : "",
        "selectedUnit" : "",
        "usingAutoFormatter" : true,
        "metricGroupName" : "",
        "alias" : " ",
        "aggregation" : "AVG",
        "splittingKey" : "BTSP1",
        "splittingValues" : [ ],
        "splittingValueColors" : { },
        "hasCustomSplittingValues" : false,
        "showOnlyLastValue" : false,
        "showOnlySplittingValue" : true,
        "customColor" : "#4a67e8"
      } ],
      "rightMeasures" : [ ],
      "overriddenAxisTitles" : [ null, null ],
      "showLegend" : true,
      "customValueLabel" : "",
      "resolutionId" : null,
      "topNItems" : null,
      "showChart" : true
    },
    "btTile" : null,
    "btListTile" : null,
    "imageTile" : null,
    "iFrameTile" : null,
    "alertTile" : null,
    "monitorSummaryTile" : null,
    "topListTile" : null,
    "textAndMeasuresTile" : null
  }, {
    "id" : "c14a7733-74ab-42e3-875e-285586daf47d",
    "name" : "",
    "tileType" : "CHART_TILE_METER",
    "overrideSession" : false,
    "session" : null,
    "overrideApplication" : false,
    "application" : null,
    "comparisonTimeframe" : false,
    "timeframe" : null,
    "description" : "Page Class Count",
    "sizeX" : 1,
    "sizeY" : 1,
    "row" : 1,
    "column" : 3,
    "bounds" : "400,0,1920,320",
    "fixed" : false,
    "chartTile" : {
      "leftMeasures" : [ {
        "id" : "49e36fa6-298f-4f5b-9fc7-3e6e4e8cccee",
        "measureIdentifier" : {
          "keyId" : "Page Types",
          "metricGroupKeyId" : "Business Transaction Results",
          "metricKeyId" : "Value",
          "parentKeyId" : "Page Types",
          "agentName" : "",
          "agentHost" : "",
          "collectorId" : "",
          "application" : ""
        },
        "name" : "Value",
        "measureType" : "TransactionMeasure",
        "unitId" : "",
        "selectedUnit" : "",
        "usingAutoFormatter" : true,
        "metricGroupName" : "",
        "alias" : "Value",
        "aggregation" : "COUNT",
        "splittingKey" : "BTSP1",
        "splittingValues" : [ ],
        "splittingValueColors" : { },
        "hasCustomSplittingValues" : false,
        "showOnlyLastValue" : false,
        "showOnlySplittingValue" : true,
        "customColor" : "#47d1c1"
      } ],
      "rightMeasures" : [ ],
      "overriddenAxisTitles" : [ null, null ],
      "showLegend" : true,
      "customValueLabel" : "",
      "resolutionId" : null,
      "topNItems" : null,
      "showChart" : true
    },
    "btTile" : null,
    "btListTile" : null,
    "imageTile" : null,
    "iFrameTile" : null,
    "alertTile" : null,
    "monitorSummaryTile" : null,
    "topListTile" : null,
    "textAndMeasuresTile" : null
  }, {
    "id" : "498beab3-fb5d-48f5-870b-e6c5489f7a6f",
    "name" : "",
    "tileType" : "TEXT_AND_MEASURE",
    "overrideSession" : false,
    "session" : null,
    "overrideApplication" : false,
    "application" : null,
    "comparisonTimeframe" : false,
    "timeframe" : null,
    "description" : "",
    "sizeX" : 1,
    "sizeY" : 1,
    "row" : 1,
    "column" : 4,
    "bounds" : "0,0,1920,80",
    "fixed" : false,
    "chartTile" : null,
    "btTile" : null,
    "btListTile" : null,
    "imageTile" : null,
    "iFrameTile" : null,
    "alertTile" : null,
    "monitorSummaryTile" : null,
    "topListTile" : null,
    "textAndMeasuresTile" : {
      "markDownText" : "{color:3399ff}{style:font-size: 1em} **Page Class Performance** {style}{color}",
      "editableMeasures" : [ ],
      "measureSplittingsMap" : { },
      "customValues" : { },
      "css" : ""
    }
  }, {
    "id" : "9b8cd48c-08d2-40e8-b5e8-dec9a30cbfdf",
    "name" : "",
    "tileType" : "TEXT_AND_MEASURE",
    "overrideSession" : false,
    "session" : null,
    "overrideApplication" : false,
    "application" : null,
    "comparisonTimeframe" : false,
    "timeframe" : null,
    "description" : "",
    "sizeX" : 1,
    "sizeY" : 1,
    "row" : 2,
    "column" : 2,
    "bounds" : "720,0,1920,80",
    "fixed" : false,
    "chartTile" : null,
    "btTile" : null,
    "btListTile" : null,
    "imageTile" : null,
    "iFrameTile" : null,
    "alertTile" : null,
    "monitorSummaryTile" : null,
    "topListTile" : null,
    "textAndMeasuresTile" : {
      "markDownText" : "{color:3399ff}{style:font-size: 1em} **Page Class Performance and Error Breakdown** {style}{color}",
      "editableMeasures" : [ ],
      "measureSplittingsMap" : { },
      "customValues" : { },
      "css" : ""
    }
  }, {
    "id" : "736e59de-b090-4727-a4cf-188bfefd1506",
    "name" : "Last 6 Hours",
    "tileType" : "BUSINESS_TRANSACTION_LIST_TILE",
    "overrideSession" : false,
    "session" : null,
    "overrideApplication" : false,
    "application" : null,
    "comparisonTimeframe" : false,
    "timeframe" : {
      "type" : "OFFSET",
      "offsetDurationValue" : 6,
      "offsetDurationUnit" : "HOURS",
      "offsetShiftValue" : null,
      "offsetShiftUnit" : null,
      "customRangeStart" : null,
      "customRangeEnd" : null
    },
    "description" : null,
    "sizeX" : 1,
    "sizeY" : 1,
    "row" : 0,
    "column" : 0,
    "bounds" : "800,0,640,480",
    "fixed" : false,
    "chartTile" : null,
    "btTile" : null,
    "btListTile" : {
      "businessTransactionId" : "Page Types",
      "resultMeasures" : [ {
        "measureIdentifier" : {
          "keyId" : "Page Types",
          "metricGroupKeyId" : "Business Transaction Results",
          "metricKeyId" : "Value",
          "parentKeyId" : "Page Types",
          "agentName" : "",
          "agentHost" : "",
          "collectorId" : "",
          "application" : ""
        },
        "aggregations" : [ "AVG", "PCT90" ],
        "name" : "PurePath Response Time",
        "selectedSortAggregation" : null
      } ],
      "selectedSplittingKey" : "BTSP1",
      "columnDisplayName" : "",
      "sortAscending" : false
    },
    "imageTile" : null,
    "iFrameTile" : null,
    "alertTile" : null,
    "monitorSummaryTile" : null,
    "topListTile" : null,
    "textAndMeasuresTile" : null
  }, {
    "id" : "50e7341a-1f4a-444f-b204-2732c27490b1",
    "name" : "Last 24 Hours",
    "tileType" : "BUSINESS_TRANSACTION_LIST_TILE",
    "overrideSession" : false,
    "session" : null,
    "overrideApplication" : false,
    "application" : null,
    "comparisonTimeframe" : false,
    "timeframe" : {
      "type" : "LAST_24_H",
      "offsetDurationValue" : null,
      "offsetDurationUnit" : null,
      "offsetShiftValue" : null,
      "offsetShiftUnit" : null,
      "customRangeStart" : null,
      "customRangeEnd" : null
    },
    "description" : null,
    "sizeX" : 1,
    "sizeY" : 1,
    "row" : 0,
    "column" : 0,
    "bounds" : "800,640,640,480",
    "fixed" : false,
    "chartTile" : null,
    "btTile" : null,
    "btListTile" : {
      "businessTransactionId" : "Page Types",
      "resultMeasures" : [ {
        "measureIdentifier" : {
          "keyId" : "Page Types",
          "metricGroupKeyId" : "Business Transaction Results",
          "metricKeyId" : "Value",
          "parentKeyId" : "Page Types",
          "agentName" : "",
          "agentHost" : "",
          "collectorId" : "",
          "application" : ""
        },
        "aggregations" : [ "AVG", "PCT90" ],
        "name" : "PurePath Response Time",
        "selectedSortAggregation" : null
      } ],
      "selectedSplittingKey" : "BTSP1",
      "columnDisplayName" : "",
      "sortAscending" : false
    },
    "imageTile" : null,
    "iFrameTile" : null,
    "alertTile" : null,
    "monitorSummaryTile" : null,
    "topListTile" : null,
    "textAndMeasuresTile" : null
  }, {
    "id" : "578bd193-b86d-4a7e-b333-05b5042d7fb8",
    "name" : "Last 7 Days",
    "tileType" : "BUSINESS_TRANSACTION_LIST_TILE",
    "overrideSession" : false,
    "session" : null,
    "overrideApplication" : false,
    "application" : null,
    "comparisonTimeframe" : false,
    "timeframe" : {
      "type" : "LAST_7_D",
      "offsetDurationValue" : null,
      "offsetDurationUnit" : null,
      "offsetShiftValue" : null,
      "offsetShiftUnit" : null,
      "customRangeStart" : null,
      "customRangeEnd" : null
    },
    "description" : null,
    "sizeX" : 1,
    "sizeY" : 1,
    "row" : 0,
    "column" : 0,
    "bounds" : "800,1280,640,480",
    "fixed" : false,
    "chartTile" : null,
    "btTile" : null,
    "btListTile" : {
      "businessTransactionId" : "Page Types",
      "resultMeasures" : [ {
        "measureIdentifier" : {
          "keyId" : "Page Types",
          "metricGroupKeyId" : "Business Transaction Results",
          "metricKeyId" : "Value",
          "parentKeyId" : "Page Types",
          "agentName" : "",
          "agentHost" : "",
          "collectorId" : "",
          "application" : ""
        },
        "aggregations" : [ "AVG", "PCT90" ],
        "name" : "PurePath Response Time",
        "selectedSortAggregation" : null
      } ],
      "selectedSplittingKey" : "BTSP1",
      "columnDisplayName" : "",
      "sortAscending" : false
    },
    "imageTile" : null,
    "iFrameTile" : null,
    "alertTile" : null,
    "monitorSummaryTile" : null,
    "topListTile" : null,
    "textAndMeasuresTile" : null
  } ],
  "logo" : "",
  "nocMode" : false,
  "zoomMode" : "FIT_WIDTH"
}