{
  "timeframe" : {
    "type" : "LAST_24_H",
    "offsetDurationValue" : null,
    "offsetDurationUnit" : null,
    "offsetShiftValue" : null,
    "offsetShiftUnit" : null,
    "customRangeStart" : null,
    "customRangeEnd" : null
  },
  "session" : {
    "name" : "y_Production",
    "id" : "y_Production",
    "sessionType" : "live",
    "timeFrameStart" : -1,
    "timeFrameEnd" : -1
  },
  "application" : null,
  "locked" : false,
  "tiles" : [ {
    "id" : "0eaba6c1-574b-4959-af3f-1a894f93c832",
    "name" : "",
    "tileType" : "CHART_TILE_BAR",
    "overrideApplication" : false,
    "application" : null,
    "timeframe" : null,
    "description" : "DB Calls Per Job",
    "sizeX" : 1,
    "sizeY" : 1,
    "row" : 1,
    "column" : 1,
    "bounds" : "400,0,1920,240",
    "fixed" : false,
    "chartTile" : {
      "leftMeasures" : [ {
        "id" : "caf89cef-b696-478d-a594-5b489caae062",
        "measureIdentifier" : {
          "keyId" : "Cron Job Invocations (DB Count;Database;Execution Count)",
          "metricGroupKeyId" : "Business Transaction Results",
          "metricKeyId" : "Value",
          "parentKeyId" : "Cron Job Invocations (DB Count;Database;Execution Count)",
          "agentName" : "",
          "agentHost" : "",
          "collectorId" : "",
          "application" : ""
        },
        "name" : "Value",
        "measureType" : "TransactionMeasure",
        "unitId" : "",
        "selectedUnit" : "",
        "usingAutoFormatter" : true,
        "metricGroupName" : "",
        "alias" : "Max",
        "aggregation" : "MAX",
        "splittingKey" : "BTSP1",
        "splittingValues" : [ ],
        "splittingValueColors" : { },
        "hasCustomSplittingValues" : false,
        "showOnlyLastValue" : false,
        "showOnlySplittingValue" : false,
        "customColor" : "#80c0c0"
      } ],
      "rightMeasures" : [ ],
      "overriddenAxisTitles" : [ null, null ],
      "showLegend" : false,
      "customValueLabel" : null,
      "resolutionId" : null,
      "topNItems" : null,
      "showChart" : true
    },
    "btTile" : null,
    "btListTile" : null,
    "imageTile" : null,
    "iFrameTile" : null,
    "alertTile" : null,
    "monitorSummaryTile" : null,
    "topListTile" : null,
    "textAndMeasuresTile" : null
  }, {
    "id" : "6572a2c7-2214-4fde-b89c-282f848b0fe3",
    "name" : "",
    "tileType" : "CHART_TILE_BAR",
    "overrideApplication" : false,
    "application" : null,
    "timeframe" : null,
    "description" : "Job Invocations",
    "sizeX" : 1,
    "sizeY" : 1,
    "row" : 1,
    "column" : 2,
    "bounds" : "80,0,1920,240",
    "fixed" : false,
    "chartTile" : {
      "leftMeasures" : [ {
        "id" : "c44a9e76-27fc-40f6-8ac5-01b020d2df87",
        "measureIdentifier" : {
          "keyId" : "Cron Job Invocations (PurePath Response Time;PurePaths;PurePath Response Time)",
          "metricGroupKeyId" : "Business Transaction Results",
          "metricKeyId" : "Value",
          "parentKeyId" : "Cron Job Invocations (PurePath Response Time;PurePaths;PurePath Response Time)",
          "agentName" : "",
          "agentHost" : "",
          "collectorId" : "",
          "application" : ""
        },
        "name" : "Value",
        "measureType" : "TransactionMeasure",
        "unitId" : "",
        "selectedUnit" : "",
        "usingAutoFormatter" : true,
        "metricGroupName" : "",
        "alias" : "Count",
        "aggregation" : "COUNT",
        "splittingKey" : "BTSP1",
        "splittingValues" : [ ],
        "splittingValueColors" : { },
        "hasCustomSplittingValues" : false,
        "showOnlyLastValue" : false,
        "showOnlySplittingValue" : false,
        "customColor" : "#408080"
      } ],
      "rightMeasures" : [ ],
      "overriddenAxisTitles" : [ null, null ],
      "showLegend" : false,
      "customValueLabel" : null,
      "resolutionId" : null,
      "topNItems" : null,
      "showChart" : true
    },
    "btTile" : null,
    "btListTile" : null,
    "imageTile" : null,
    "iFrameTile" : null,
    "alertTile" : null,
    "monitorSummaryTile" : null,
    "topListTile" : null,
    "textAndMeasuresTile" : null
  }, {
    "id" : "0eaa2d6e-2f9b-42fc-be0a-e6ac4d9d566e",
    "name" : "",
    "tileType" : "TEXT_AND_MEASURE",
    "overrideApplication" : false,
    "application" : null,
    "timeframe" : null,
    "description" : "",
    "sizeX" : 1,
    "sizeY" : 1,
    "row" : 1,
    "column" : 4,
    "bounds" : "320,0,1920,80",
    "fixed" : false,
    "chartTile" : null,
    "btTile" : null,
    "btListTile" : null,
    "imageTile" : null,
    "iFrameTile" : null,
    "alertTile" : null,
    "monitorSummaryTile" : null,
    "topListTile" : null,
    "textAndMeasuresTile" : {
      "markDownText" : "{color:3399ff}{style:font-size: 1em} **Cron Job DB Impact** {style}{color}",
      "editableMeasures" : [ ],
      "measureSplittingsMap" : { },
      "customValues" : { }
    }
  }, {
    "id" : "6a368602-0782-44f0-90ca-caa7a6c9f4da",
    "name" : "",
    "tileType" : "TEXT_AND_MEASURE",
    "overrideApplication" : false,
    "application" : null,
    "timeframe" : null,
    "description" : "",
    "sizeX" : 1,
    "sizeY" : 1,
    "row" : 2,
    "column" : 1,
    "bounds" : "0,0,1920,80",
    "fixed" : false,
    "chartTile" : null,
    "btTile" : null,
    "btListTile" : null,
    "imageTile" : null,
    "iFrameTile" : null,
    "alertTile" : null,
    "monitorSummaryTile" : null,
    "topListTile" : null,
    "textAndMeasuresTile" : {
      "markDownText" : "{color:3399ff}{style:font-size: 1em} **Cron Job Invocations** {style}{color}",
      "editableMeasures" : [ ],
      "measureSplittingsMap" : { },
      "customValues" : { }
    }
  }, {
    "id" : "eb3cd226-c147-4de6-bb5b-f7ad598ae8d9",
    "name" : "Last 24 Hours",
    "tileType" : "BUSINESS_TRANSACTION_LIST_TILE",
    "overrideApplication" : false,
    "application" : null,
    "timeframe" : {
      "type" : "LAST_24_H",
      "offsetDurationValue" : null,
      "offsetDurationUnit" : null,
      "offsetShiftValue" : null,
      "offsetShiftUnit" : null,
      "customRangeStart" : null,
      "customRangeEnd" : null
    },
    "description" : "",
    "sizeX" : 1,
    "sizeY" : 1,
    "row" : 2,
    "column" : 2,
    "bounds" : "720,0,640,480",
    "fixed" : false,
    "chartTile" : null,
    "btTile" : null,
    "btListTile" : {
      "businessTransactionId" : "Cron Job Invocations",
      "resultMeasures" : [ {
        "measureIdentifier" : {
          "keyId" : "Cron Job Invocations (PurePath Response Time;PurePaths;PurePath Response Time)",
          "metricGroupKeyId" : "Business Transaction Results",
          "metricKeyId" : "Value",
          "parentKeyId" : "Cron Job Invocations (PurePath Response Time;PurePaths;PurePath Response Time)",
          "agentName" : "",
          "agentHost" : "",
          "collectorId" : "",
          "application" : ""
        },
        "aggregations" : [ "AVG" ],
        "name" : "PurePath Response Time",
        "selectedSortAggregation" : null
      }, {
        "measureIdentifier" : {
          "keyId" : "Cron Job Invocations (DB Count;Database;Execution Count)",
          "metricGroupKeyId" : "Business Transaction Results",
          "metricKeyId" : "Value",
          "parentKeyId" : "Cron Job Invocations (DB Count;Database;Execution Count)",
          "agentName" : "",
          "agentHost" : "",
          "collectorId" : "",
          "application" : ""
        },
        "aggregations" : [ "AVG" ],
        "name" : "DB Count",
        "selectedSortAggregation" : null
      } ],
      "selectedSplittingKey" : "BTSP1",
      "columnDisplayName" : "",
      "sortAscending" : false
    },
    "imageTile" : null,
    "iFrameTile" : null,
    "alertTile" : null,
    "monitorSummaryTile" : null,
    "topListTile" : null,
    "textAndMeasuresTile" : null
  }, {
    "id" : "b10ab89b-597c-4e88-911a-3af2e632e24b",
    "name" : "",
    "tileType" : "TEXT_AND_MEASURE",
    "overrideApplication" : false,
    "application" : null,
    "timeframe" : null,
    "description" : "",
    "sizeX" : 1,
    "sizeY" : 1,
    "row" : 2,
    "column" : 3,
    "bounds" : "640,0,1920,80",
    "fixed" : false,
    "chartTile" : null,
    "btTile" : null,
    "btListTile" : null,
    "imageTile" : null,
    "iFrameTile" : null,
    "alertTile" : null,
    "monitorSummaryTile" : null,
    "topListTile" : null,
    "textAndMeasuresTile" : {
      "markDownText" : "{color:3399ff}{style:font-size: 1em} **Cron Job Invocations** {style}{color}",
      "editableMeasures" : [ ],
      "measureSplittingsMap" : { },
      "customValues" : { }
    }
  }, {
    "id" : "8d268b24-4182-403a-9096-666315e24ac1",
    "name" : "Previous 24 Hours",
    "tileType" : "BUSINESS_TRANSACTION_LIST_TILE",
    "overrideApplication" : false,
    "application" : null,
    "timeframe" : {
      "type" : "OFFSET",
      "offsetDurationValue" : 24,
      "offsetDurationUnit" : "HOURS",
      "offsetShiftValue" : 24,
      "offsetShiftUnit" : "HOURS",
      "customRangeStart" : null,
      "customRangeEnd" : null
    },
    "description" : "",
    "sizeX" : 1,
    "sizeY" : 1,
    "row" : 0,
    "column" : 0,
    "bounds" : "720,640,640,480",
    "fixed" : false,
    "chartTile" : null,
    "btTile" : null,
    "btListTile" : {
      "businessTransactionId" : "Cron Job Invocations",
      "resultMeasures" : [ {
        "measureIdentifier" : {
          "keyId" : "Cron Job Invocations (PurePath Response Time;PurePaths;PurePath Response Time)",
          "metricGroupKeyId" : "Business Transaction Results",
          "metricKeyId" : "Value",
          "parentKeyId" : "Cron Job Invocations (PurePath Response Time;PurePaths;PurePath Response Time)",
          "agentName" : "",
          "agentHost" : "",
          "collectorId" : "",
          "application" : ""
        },
        "aggregations" : [ "AVG" ],
        "name" : "PurePath Response Time",
        "selectedSortAggregation" : null
      }, {
        "measureIdentifier" : {
          "keyId" : "Cron Job Invocations (DB Count;Database;Execution Count)",
          "metricGroupKeyId" : "Business Transaction Results",
          "metricKeyId" : "Value",
          "parentKeyId" : "Cron Job Invocations (DB Count;Database;Execution Count)",
          "agentName" : "",
          "agentHost" : "",
          "collectorId" : "",
          "application" : ""
        },
        "aggregations" : [ "AVG" ],
        "name" : "DB Count",
        "selectedSortAggregation" : null
      } ],
      "selectedSplittingKey" : "BTSP1",
      "columnDisplayName" : "",
      "sortAscending" : false
    },
    "imageTile" : null,
    "iFrameTile" : null,
    "alertTile" : null,
    "monitorSummaryTile" : null,
    "topListTile" : null,
    "textAndMeasuresTile" : null
  }, {
    "id" : "1469ce53-6c33-4007-b7ea-9dba2d3e05a4",
    "name" : "Last 7 Days",
    "tileType" : "BUSINESS_TRANSACTION_LIST_TILE",
    "overrideApplication" : false,
    "application" : null,
    "timeframe" : {
      "type" : "OFFSET",
      "offsetDurationValue" : 7,
      "offsetDurationUnit" : "DAYS",
      "offsetShiftValue" : null,
      "offsetShiftUnit" : null,
      "customRangeStart" : null,
      "customRangeEnd" : null
    },
    "description" : "",
    "sizeX" : 1,
    "sizeY" : 1,
    "row" : 0,
    "column" : 0,
    "bounds" : "720,1280,640,480",
    "fixed" : false,
    "chartTile" : null,
    "btTile" : null,
    "btListTile" : {
      "businessTransactionId" : "Cron Job Invocations",
      "resultMeasures" : [ {
        "measureIdentifier" : {
          "keyId" : "Cron Job Invocations (PurePath Response Time;PurePaths;PurePath Response Time)",
          "metricGroupKeyId" : "Business Transaction Results",
          "metricKeyId" : "Value",
          "parentKeyId" : "Cron Job Invocations (PurePath Response Time;PurePaths;PurePath Response Time)",
          "agentName" : "",
          "agentHost" : "",
          "collectorId" : "",
          "application" : ""
        },
        "aggregations" : [ "AVG" ],
        "name" : "PurePath Response Time",
        "selectedSortAggregation" : null
      }, {
        "measureIdentifier" : {
          "keyId" : "Cron Job Invocations (DB Count;Database;Execution Count)",
          "metricGroupKeyId" : "Business Transaction Results",
          "metricKeyId" : "Value",
          "parentKeyId" : "Cron Job Invocations (DB Count;Database;Execution Count)",
          "agentName" : "",
          "agentHost" : "",
          "collectorId" : "",
          "application" : ""
        },
        "aggregations" : [ "AVG" ],
        "name" : "DB Count",
        "selectedSortAggregation" : null
      } ],
      "selectedSplittingKey" : "BTSP1",
      "columnDisplayName" : "",
      "sortAscending" : false
    },
    "imageTile" : null,
    "iFrameTile" : null,
    "alertTile" : null,
    "monitorSummaryTile" : null,
    "topListTile" : null,
    "textAndMeasuresTile" : null
  } ],
  "logo" : "",
  "nocMode" : false,
  "zoomMode" : "FIT_WIDTH"
}